autoact/__init__.py
autoact/autoact.py
autoact/setup.py
autoact/utils.py
autoact/core/__init__.py
autoact/core/action_manager.py
autoact/core/action_resolver/__init__.py
autoact/core/action_resolver/common_resolver.py
autoact/examples/__init__.py
autoact/examples/dummy_module.py
auto_action-0.0.1.dist-info/LICENSE
auto_action-0.0.1.dist-info/METADATA
auto_action-0.0.1.dist-info/WHEEL
auto_action-0.0.1.dist-info/entry_points.txt
auto_action-0.0.1.dist-info/top_level.txt
auto_action-0.0.1.dist-info/RECORD
