Metadata-Version: 2.1
Name: auto-action
Version: 0.0.1
Summary: UNKNOWN
Home-page: UNKNOWN
Author: Xinyao(Alvin) Sun
Author-email: xinyao1@ualberta.ca
License: UNKNOWN
Platform: UNKNOWN
Requires-Dist: pyyaml
